{"ticker":"BOOT.L","name":"Henry Boot PLC","signal":"buy","version":1,"created_at":"2026-07-18T12:39:33.249358+00:00","updated_at":"2026-07-18T12:39:33.249358+00:00","mode":"initial","executive_summary":"# Henry Boot PLC (BOOT.L) — Research Memo\n\n**Quantitative screen:** Buy (7/22 models, composite 66%)  \n**Sources:** Filings index (28 RNS entries, 0 body extracts); Yahoo `financials_annual.json` (primary figures — filing bodies unavailable); screening snapshot; news manifest.\n\n---\n\n## EXECUTIVE SUMMARY\n\nHenry Boot is a UK land-led property group (Hallam Land, Stonebridge Homes, commercial development) trading at a deep discount to book: P/B ~0.5, P/E ~10, dividend yield ~4.8%. The quantitative screen flags cheapness, dividend quality, and balance-sheet resilience (current ratio ~4.9), with a stable buy signal over five weeks. The investment case rests on a large land bank and development pipeline — including the Golden Valley cyber hub — versus cyclical UK housing/planning risk and weak reported ROE (~4%). Key debate: whether NAV and land-sale optionality are mispriced, or whether negative free cash flow, rising net debt, and management transition cap upside.\n\n---\n\n## INVESTMENT THESIS\n\nFor a value investor, BOOT screens as a classic asset play on UK residential and commercial land rather than a pure housebuilder. Seven of 22 models pass, spanning Graham Defensive, Schloss low P/B, earnings yield, low P/E plus high yield, dividend growth, composite value, and financial health — three of four factor families (cheapness, dividend, risk). At P/B 0.52 and P/E 10.2, the market prices equity well below Yahoo-reported book value of ~£423m (FY25) and net assets heavily weighted to inventory (~£368m) and investment property (~£95m).\n\nBusiness quality is mixed but defensible: long operating history, family-influenced stewardship, recurring land sales, and a pivot toward higher-margin prime developments and premium homes (per Mar 2026 earnings commentary). Portfolio simplification — construction division MBO (~£4m, completed Jan 2026) and asset recycling — supports a capital-light, land-bank model. Dividend continuity (~£10.5m paid in FY25) aligns with the dividend-growth screen pass.\n\nThe screen’s buy signal is not a quality-growth call: ROE is only 4.3% and revenue has contracted post-disposal. The thesis is that tangible NAV, planning gains on strategic sites (Golden Valley, Arcadis letting), and a 4.8% yield offer asymmetric upside if UK planning and housing demand stabilise. Conviction from the screen is moderate (38%) but persistent.\n\n---\n\n## FINANCIAL REVIEW\n\n**Source gap:** The filings index lists 28 UK RNS items (regime: `uk_rns`) but **zero downloadable body extracts** under `filings/bodies/`. No annual report text is indexed (`annual: 0`). One interim item is tagged — “Trading Update” (16 Jul 2026) — without body. Headlines also reference “Results for the year ended 31 March 2026” (25 Jun 2026) and various corporate updates, but figures cannot be verified from primary filings. **All quantitative analysis below uses Yahoo `financials_annual.json` (fallback).**\n\n### Annual trend (Yahoo, year-end 31 March)\n\n| Metric | FY22 | FY23 | FY24 | FY25 |\n|--------|------|------|------|------|\n| Revenue | £341.4m | £359.4m | £266.2m | £251.5m |\n| Operating income | £41.1m | £37.2m | £29.5m | £25.2m |\n| EBITDA | £53.2m | £49.4m | £47.1m | £39.8m |\n| Net income | £33.3m | £26.3m | £23.3m | £23.5m |\n| Free cash flow | −£31.6m | −£15.5m | +£24.2m | −£32.3m |\n\nRevenue peaked in FY23 and fell ~30% by FY25, consistent with portfolio reshaping and the construction exit. Reported net income has been resilient (£23–33m), aided by FY25 discontinued-operation profit of £2.2m. Operating margin compression (operating income/revenue from ~11% toward ~10%) reflects a softer top line and higher interest burden.\n\n### Balance sheet and capital structure (FY25 Yahoo)\n\n- **Total assets:** £654.4m; **equity:** £422.7m (minority interest −£2.5m).\n- **Inventory:** £368.1m (+£35m YoY) — core land bank; finished goods £283m.\n- **Investment properties:** £94.6m; **net PPE:** £29.8m.\n- **Cash:** £8.4m (from £16.8m); **total debt:** £116.4m; **net debt:** £104.7m (from £58.8m).\n- **Working capital:** £361.1m; **current ratio** ~4.9 (screen metric).\n- **Defined benefit pension:** £3.0m asset (FY25) vs £9.9m (FY24) — improved but not immaterial.\n\nLeverage has risen: net debt/equity ~25%. FY25 saw £97m gross debt issuance and £59m repayment (Yahoo cash-flow), funding inventory build and dividends while operating cash flow was **−£30.9m**. Working-capital outflow (£49.9m) was driven by inventory and receivables — typical for land-led models but a near-term red flag for FCF-focused investors.\n\nScreen-reported FCF of ~£9.3m likely reflects a different calculation window or adjustment; Yahoo FY25 FCF is **−£32.3m**.\n\n### Dividends and returns\n\n- Common dividends paid: £10.5m FY25 (~4.8% yield at current price).\n- **ROE ~4.3%** (screen) — low for a “buy” on quality grounds; supports asset, not earnings, framing.\n- Interest expense £8.0m vs £8.7m prior year; net interest cost £4.0m.\n\n### Interim / recent trading (filings headlines only)\n\n- **Trading Update** (16 Jul 2026): indexed as interim; no body — figures unavailable.\n- **FY26 results** (25 Jun 2026 headline): not in Yahoo annual file; Mar 2026 earnings commentary (news) cites H2 land and property sales >£350m total (~£193m group share), revenue/completions dip, and emphasis on “high-quality land, prime developments, and premium homes.” Cannot reconcile to audited numbers without the RNS body.\n\n**Going concern / covenants:** Not assessable — no filing body text retrieved.\n\n---\n\n## RISKS AND RED FLAGS\n\n**Cyclical and operational**\n- UK housebuilding and land markets remain planning- and rate-sensitive; revenue and operating profit are on a multi-year downtrend (Yahoo).\n- Inventory-heavy balance sheet (£368m) creates mark-to-market and timing risk if land values or absorption slow.\n- Negative FY25 free cash flow and rising net debt (+£46m) increase refinancing sensitivity; cash cover is thin (£8.4m vs £116m debt).\n\n**Strategic / portfolio**\n- Construction division sale reduces diversification and near-term revenue; integration of any Care REIT transaction (Mar 2025 RNS headline) adds execution and sector (care homes/REIT) risk — terms not verified without filing body.\n- Golden Valley (~£1bn project; phase 1 funding secured Jul 2026) is long-dated (completion cited early 2028) and capital-intensive.\n\n**Governance and management**\n- **CEO succession update** (12 Jun 2026) and **directorate change** (3 Jun 2026) introduce transition risk during a leverage uptick.\n- Positive signal: **CEO share purchase** (16 Jun 2026) and **buy-back extension** (RNS, Jul 2026) suggest insider confidence, but not a substitute for audited disclosure.\n\n**Pension and regulatory**\n- Defined benefit pension exposure improved but warrants monitoring in annual report (not available).\n- Investors’ Chronicle piece, “Stay cautious with this lowly rated property stock” (23 Sep 2025), flags scepticism on property cyclicality — aligned with low ROE.\n\n**Screen limitations**\n- Quality/momentum families did not drive the signal; macro context (FTSE 100 ~10,600; GBP/USD ~1.35) is neutral backdrop only — not a veto.\n\n**Disclosure gap**\n- Absence of filing bodies prevents assessment of going-concern language, contingent liabilities, litigation, or banking covenants — a material research limitation.\n\n---\n\n## NEWS HIGHLIGHTS\n\nCoverage is **moderately thin** for dedicated sell-side research; many manifest hits are false positives (“car boot”, Boot Barn, Boots pharmacy). Material Henry Boot items:\n\n| Date | Title | Relevance |\n|------|-------|-----------|\n| 16 Jul 2026 | Trading Update — Investegate | Latest trading; no detail in manifest |\n| 13 Jul 2026 | Henry Boot secures Golden Valley phase 1 funding — Investegate / Yahoo | Major Cheltenham cyber hub; ~£1bn/£1.3bn scheme |\n| 25 Jun 2026 | Results for year ended 31 March 2026 — Investegate | Full-year results announced |\n| 16 Jun 2026 | CEO share purchase — Investegate | Insider buying |\n| 12 Jun 2026 | CEO Succession Update; Appointment of new MD at Stonebridge Homes — Investegate | Leadership changes |\n| 15 Jun 2026 | Henry Boot secures letting to Arcadis — Investegate | Commercial letting |\n| 28 Jun 2026 | “5.5%-yielding income stock at 13-year low” — The Twelfth Magpie | Retail interest in income/value |\n| 24 Mar 2026 | Henry Boot H2 / FY2025 Earnings Call Highlights — Yahoo | Land sales >£350m; revenue/completions softer |\n| 5 Jan 2026 | Henry Boot formally completes construction division sale — Construction News | Portfolio simplification |\n| 11 Mar 2025 | Recommended Cash Acquisition of Care REIT plc — Investegate | M&A strategy |\n| 22 Jan 2025 | Sale of Last Investments — Investegate | Asset recycling |\n| 23 Sep 2025 | Henry Boot sells construction arm in £4m MBO — Construction News | Strategic exit |\n| 23 Sep 2025 | Stay cautious with this lowly rated property stock — Investors’ Chronicle | Bearish third-party view |\n| 23 Jan 2026 | Returns At Henry Boot Appear To Be Weighed Down — Yahoo | ROE/returns scrutiny |\n\nNo material regulatory enforcement or accounting scandal flagged in the manifest.\n\n---\n\n## RESEARCH VERDICT\n\nVerdict: accumulate  \nRisk: medium  \nConfidence: 0.62  \nRationale: Deep discount to book, dividend yield, and land-bank optionality support the quantitative buy, but weak ROE, negative FY25 FCF, rising leverage, and missing primary filings prevent full confirmation of asset quality and covenant headroom.","investment_thesis":"","financial_review":"","risks_and_flags":"","news_highlights":"","research_verdict":null,"research_risk_level":null,"research_confidence":null,"research_rationale":null,"weekly_updates":[],"source_counts":{"financial_years":5,"news_articles":47,"filings_total":28,"filings_annual":0,"filings_interim":1,"filings_with_body":0},"agent_id":"agent-03442bfe-3865-4d11-a40a-ec62d7964c04","research_path":"docs/data/library/markets/ftse_smallcap/screen/research/BOOT.L/research.md"}