{"ticker":"RWS.L","fetched_at":"2026-07-18T18:12:35.767040+00:00","income_statement":{"2025":{"Tax Effect Of Unusual Items":-50000.0,"Tax Rate For Calcs":0.25,"Normalized EBITDA":-18000000.0,"Total Unusual Items":-200000.0,"Total Unusual Items Excluding Goodwill":-200000.0,"Net Income From Continuing Operation Net Minority Interest":-99800000.0,"Reconciled Depreciation":75000000.0,"Reconciled Cost Of Revenue":390800000.0,"EBITDA":-18200000.0,"EBIT":-93200000.0,"Net Interest Income":-5700000.0,"Interest Expense":6500000.0,"Interest Income":800000.0,"Normalized Income":-99650000.0,"Net Income From Continuing And Discontinued Operation":-99800000.0,"Total Expenses":783900000.0,"Total Operating Income As Reported":-93800000.0,"Diluted Average Shares":370022467.0,"Basic Average Shares":369463383.0,"Diluted EPS":-0.27,"Basic EPS":-0.27,"Diluted NI Availto Com Stockholders":-99800000.0,"Net Income Common Stockholders":-99800000.0,"Otherunder Preferred Stock Dividend":0.0,"Net Income":-99800000.0,"Net Income Including Noncontrolling Interests":-99800000.0,"Net Income Continuous Operations":-99800000.0,"Tax Provision":100000.0,"Pretax Income":-99700000.0,"Special Income Charges":-200000.0,"Other Special Charges":200000.0,"Net Non Operating Interest Income Expense":-5700000.0,"Interest Expense Non Operating":6500000.0,"Interest Income Non Operating":800000.0,"Operating Income":-93800000.0,"Operating Expense":393100000.0,"Selling General And Administration":393100000.0,"General And Administrative Expense":393100000.0,"Gross Profit":299300000.0,"Cost Of Revenue":390800000.0,"Total Revenue":690100000.0,"Operating Revenue":690100000.0},"2024":{"Tax Effect Of Unusual Items":-41666.666667,"Tax Rate For Calcs":0.208333,"Normalized EBITDA":136000000.0,"Total Unusual Items":-200000.0,"Total Unusual Items Excluding Goodwill":-200000.0,"Net Income From Continuing Operation Net Minority Interest":47500000.0,"Reconciled Depreciation":69300000.0,"Reconciled Cost Of Revenue":381700000.0,"EBITDA":135800000.0,"EBIT":66500000.0,"Net Interest Income":-5600000.0,"Interest Expense":6500000.0,"Interest Income":900000.0,"Normalized Income":47658333.333333,"Net Income From Continuing And Discontinued Operation":47500000.0,"Total Expenses":652400000.0,"Rent Expense Supplemental":1900000.0,"Total Operating Income As Reported":65800000.0,"Diluted Average Shares":371806226.0,"Basic Average Shares":371315586.0,"Diluted EPS":0.128,"Basic EPS":0.128,"Diluted NI Availto Com Stockholders":47500000.0,"Net Income Common Stockholders":47500000.0,"Otherunder Preferred Stock Dividend":0.0,"Net Income":47500000.0,"Net Income Including Noncontrolling Interests":47500000.0,"Net Income Continuous Operations":47500000.0,"Tax Provision":12500000.0,"Pretax Income":60000000.0,"Special Income Charges":-200000.0,"Other Special Charges":200000.0,"Net Non Operating Interest Income Expense":-5600000.0,"Interest Expense Non Operating":6500000.0,"Interest Income Non Operating":900000.0,"Operating Income":65800000.0,"Operating Expense":270700000.0,"Selling General And Administration":270700000.0,"General And Administrative Expense":270700000.0,"Gross Profit":336500000.0,"Cost Of Revenue":381700000.0,"Total Revenue":718200000.0,"Operating Revenue":718200000.0},"2023":{"Tax Effect Of Unusual Items":-57000.0,"Tax Rate For Calcs":0.19,"Normalized EBITDA":67300000.0,"Total Unusual Items":-300000.0,"Total Unusual Items Excluding Goodwill":-300000.0,"Net Income From Continuing Operation Net Minority Interest":-27700000.0,"Reconciled Depreciation":73600000.0,"Reconciled Cost Of Revenue":394300000.0,"EBITDA":67000000.0,"EBIT":-6600000.0,"Net Interest Income":-3700000.0,"Interest Expense":4300000.0,"Interest Income":600000.0,"Normalized Income":-27457000.0,"Net Income From Continuing And Discontinued Operation":-27700000.0,"Total Expenses":740700000.0,"Rent Expense Supplemental":2400000.0,"Total Operating Income As Reported":-6900000.0,"Diluted Average Shares":388261978.0,"Basic Average Shares":388231290.0,"Diluted EPS":-0.071,"Basic EPS":-0.071,"Diluted NI Availto Com Stockholders":-27700000.0,"Net Income Common Stockholders":-27700000.0,"Otherunder Preferred Stock Dividend":0.0,"Net Income":-27700000.0,"Net Income Including Noncontrolling Interests":-27700000.0,"Net Income Continuous Operations":-27700000.0,"Tax Provision":16800000.0,"Pretax Income":-10900000.0,"Special Income Charges":-300000.0,"Other Special Charges":300000.0,"Net Non Operating Interest Income Expense":-3700000.0,"Total Other Finance Cost":600000.0,"Interest Expense Non Operating":4300000.0,"Interest Income Non Operating":600000.0,"Operating Income":-6900000.0,"Operating Expense":346400000.0,"Selling General And Administration":346400000.0,"General And Administrative Expense":346400000.0,"Gross Profit":339500000.0,"Cost Of Revenue":394300000.0,"Total Revenue":733800000.0,"Operating Revenue":733800000.0},"2022":{"Tax Effect Of Unusual Items":-73800.0,"Tax Rate For Calcs":0.246,"Normalized EBITDA":154500000.0,"Total Unusual Items":-300000.0,"Total Unusual Items Excluding Goodwill":-300000.0,"Net Income From Continuing Operation Net Minority Interest":62700000.0,"Reconciled Depreciation":68000000.0,"Reconciled Cost Of Revenue":399000000.0,"EBITDA":154200000.0,"EBIT":86200000.0,"Net Interest Income":-2800000.0,"Interest Expense":3000000.0,"Interest Income":200000.0,"Normalized Income":62926200.0,"Net Income From Continuing And Discontinued Operation":62700000.0,"Total Expenses":662900000.0,"Rent Expense Supplemental":2300000.0,"Total Operating Income As Reported":86300000.0,"Diluted Average Shares":390844368.0,"Basic Average Shares":389374854.0,"Diluted EPS":0.16,"Basic EPS":0.161,"Diluted NI Availto Com Stockholders":62700000.0,"Net Income Common Stockholders":62700000.0,"Otherunder Preferred Stock Dividend":0.0,"Net Income":62700000.0,"Net Income Including Noncontrolling Interests":62700000.0,"Net Income Continuous Operations":62700000.0,"Tax Provision":20500000.0,"Pretax Income":83200000.0,"Special Income Charges":-300000.0,"Other Special Charges":300000.0,"Net Non Operating Interest Income Expense":-2800000.0,"Total Other Finance Cost":300000.0,"Interest Expense Non Operating":3000000.0,"Interest Income Non Operating":200000.0,"Operating Income":86300000.0,"Operating Expense":263900000.0,"Selling General And Administration":263900000.0,"General And Administrative Expense":263900000.0,"Gross Profit":350200000.0,"Cost Of Revenue":399000000.0,"Total Revenue":749200000.0,"Operating Revenue":749200000.0},"2021":{"Rent Expense Supplemental":2200000.0,"Total Other Finance Cost":300000.0}},"balance_sheet":{"2025":{"Ordinary Shares Number":369807646.0,"Share Issued":369807646.0,"Net Debt":25400000.0,"Total Debt":80500000.0,"Tangible Book Value":600000.0,"Invested Capital":821200000.0,"Working Capital":81700000.0,"Net Tangible Assets":600000.0,"Capital Lease Obligations":22500000.0,"Common Stock Equity":763200000.0,"Total Capitalization":821200000.0,"Total Equity Gross Minority Interest":763200000.0,"Stockholders Equity":763200000.0,"Other Equity Interest":9300000.0,"Retained Earnings":104500000.0,"Additional Paid In Capital":56000000.0,"Capital Stock":3700000.0,"Common Stock":3700000.0,"Total Liabilities Net Minority Interest":277700000.0,"Total Non Current Liabilities Net Minority Interest":113600000.0,"Non Current Deferred Revenue":100000.0,"Non Current Deferred Taxes Liabilities":37200000.0,"Long Term Debt And Capital Lease Obligation":74900000.0,"Long Term Capital Lease Obligation":16900000.0,"Long Term Debt":58000000.0,"Long Term Provisions":1400000.0,"Current Liabilities":164100000.0,"Current Debt And Capital Lease Obligation":5600000.0,"Current Capital Lease Obligation":5600000.0,"Current Provisions":10300000.0,"Payables":49400000.0,"Other Payable":13600000.0,"Total Tax Payable":13700000.0,"Accounts Payable":22100000.0,"Total Assets":1040900000.0,"Total Non Current Assets":795100000.0,"Non Current Deferred Taxes Assets":1700000.0,"Goodwill And Other Intangible Assets":762600000.0,"Other Intangible Assets":276700000.0,"Goodwill":485900000.0,"Net PPE":28700000.0,"Accumulated Depreciation":-34900000.0,"Gross PPE":63600000.0,"Other Properties":19700000.0,"Machinery Furniture Equipment":36100000.0,"Buildings And Improvements":7800000.0,"Land And Improvements":0.0,"Properties":0.0,"Current Assets":245800000.0,"Assets Held For Sale Current":3500000.0,"Prepaid Assets":16300000.0,"Other Receivables":63400000.0,"Taxes Receivable":5400000.0,"Accounts Receivable":124600000.0,"Allowance For Doubtful Accounts Receivable":-3400000.0,"Gross Accounts Receivable":128000000.0,"Cash Cash Equivalents And Short Term Investments":32600000.0,"Cash And Cash Equivalents":32600000.0,"Cash Equivalents":6700000.0,"Cash Financial":25900000.0},"2024":{"Treasury Shares Number":0.0,"Ordinary Shares Number":368717980.0,"Share Issued":368717980.0,"Net Debt":12900000.0,"Total Debt":101600000.0,"Tangible Book Value":11800000.0,"Invested Capital":974000000.0,"Working Capital":119900000.0,"Net Tangible Assets":11800000.0,"Capital Lease Obligations":27200000.0,"Common Stock Equity":899600000.0,"Total Capitalization":974000000.0,"Total Equity Gross Minority Interest":899600000.0,"Stockholders Equity":899600000.0,"Other Equity Interest":8100000.0,"Retained Earnings":249100000.0,"Additional Paid In Capital":54500000.0,"Capital Stock":3700000.0,"Common Stock":3700000.0,"Total Liabilities Net Minority Interest":306900000.0,"Total Non Current Liabilities Net Minority Interest":148500000.0,"Non Current Pension And Other Postretirement Benefit Plans":0.0,"Non Current Deferred Revenue":400000.0,"Non Current Deferred Taxes Liabilities":53500000.0,"Long Term Debt And Capital Lease Obligation":93100000.0,"Long Term Capital Lease Obligation":18700000.0,"Long Term Debt":74400000.0,"Long Term Provisions":1500000.0,"Current Liabilities":158400000.0,"Current Deferred Taxes Liabilities":2800000.0,"Current Debt And Capital Lease Obligation":8500000.0,"Current Capital Lease Obligation":8500000.0,"Pensionand Other Post Retirement Benefit Plans Current":1800000.0,"Current Provisions":7900000.0,"Payables":52400000.0,"Other Payable":11200000.0,"Total Tax Payable":16100000.0,"Accounts Payable":25100000.0,"Total Assets":1206500000.0,"Total Non Current Assets":928200000.0,"Non Current Deferred Taxes Assets":2000000.0,"Goodwill And Other Intangible Assets":887800000.0,"Other Intangible Assets":317000000.0,"Goodwill":570800000.0,"Net PPE":36200000.0,"Accumulated Depreciation":-44800000.0,"Gross PPE":81000000.0,"Other Properties":22700000.0,"Machinery Furniture Equipment":34100000.0,"Buildings And Improvements":7200000.0,"Land And Improvements":17000000.0,"Properties":0.0,"Current Assets":278300000.0,"Other Current Assets":-100000.0,"Assets Held For Sale Current":0.0,"Prepaid Assets":18600000.0,"Other Receivables":66700000.0,"Taxes Receivable":5600000.0,"Accounts Receivable":125900000.0,"Allowance For Doubtful Accounts Receivable":-3400000.0,"Gross Accounts Receivable":129300000.0,"Cash Cash Equivalents And Short Term Investments":61500000.0,"Cash And Cash Equivalents":61500000.0,"Cash Equivalents":9100000.0,"Cash Financial":52400000.0},"2023":{"Treasury Shares Number":30688.0,"Ordinary Shares Number":381572638.0,"Share Issued":381603326.0,"Total Debt":86100000.0,"Tangible Book Value":19300000.0,"Invested Capital":1039900000.0,"Working Capital":107600000.0,"Net Tangible Assets":19300000.0,"Capital Lease Obligations":33500000.0,"Common Stock Equity":987300000.0,"Total Capitalization":1039900000.0,"Total Equity Gross Minority Interest":987300000.0,"Stockholders Equity":987300000.0,"Other Equity Interest":5300000.0,"Retained Earnings":277600000.0,"Additional Paid In Capital":54500000.0,"Capital Stock":3800000.0,"Common Stock":3800000.0,"Total Liabilities Net Minority Interest":328500000.0,"Total Non Current Liabilities Net Minority Interest":145900000.0,"Non Current Pension And Other Postretirement Benefit Plans":0.0,"Non Current Deferred Revenue":2300000.0,"Non Current Deferred Taxes Liabilities":61100000.0,"Long Term Debt And Capital Lease Obligation":76200000.0,"Long Term Capital Lease Obligation":23600000.0,"Long Term Debt":52600000.0,"Long Term Provisions":6300000.0,"Current Liabilities":182600000.0,"Current Deferred Taxes Liabilities":0.0,"Current Debt And Capital Lease Obligation":9900000.0,"Current Capital Lease Obligation":9900000.0,"Pensionand Other Post Retirement Benefit Plans Current":6800000.0,"Current Provisions":800000.0,"Payables":57000000.0,"Other Payable":11500000.0,"Total Tax Payable":19800000.0,"Accounts Payable":25700000.0,"Total Assets":1315800000.0,"Total Non Current Assets":1025600000.0,"Non Current Deferred Taxes Assets":1200000.0,"Goodwill And Other Intangible Assets":968000000.0,"Other Intangible Assets":359400000.0,"Goodwill":608600000.0,"Net PPE":55000000.0,"Accumulated Depreciation":-33300000.0,"Gross PPE":88300000.0,"Other Properties":27500000.0,"Machinery Furniture Equipment":35800000.0,"Buildings And Improvements":35500000.0,"Land And Improvements":17000000.0,"Properties":0.0,"Current Assets":290200000.0,"Prepaid Assets":15000000.0,"Other Receivables":58700000.0,"Taxes Receivable":1700000.0,"Accounts Receivable":138600000.0,"Allowance For Doubtful Accounts Receivable":-1800000.0,"Gross Accounts Receivable":140400000.0,"Cash Cash Equivalents And Short Term Investments":76200000.0,"Cash And Cash Equivalents":76200000.0,"Cash Equivalents":7700000.0,"Cash Financial":68500000.0},"2022":{"Treasury Shares Number":55896.0,"Ordinary Shares Number":389407914.0,"Share Issued":389463810.0,"Total Debt":76000000.0,"Tangible Book Value":63700000.0,"Invested Capital":1171000000.0,"Working Capital":122300000.0,"Net Tangible Assets":63700000.0,"Capital Lease Obligations":46700000.0,"Common Stock Equity":1141700000.0,"Total Capitalization":1171000000.0,"Total Equity Gross Minority Interest":1141700000.0,"Stockholders Equity":1141700000.0,"Other Equity Interest":6000000.0,"Retained Earnings":371100000.0,"Additional Paid In Capital":54400000.0,"Capital Stock":3900000.0,"Common Stock":3900000.0,"Total Liabilities Net Minority Interest":334600000.0,"Total Non Current Liabilities Net Minority Interest":131000000.0,"Non Current Pension And Other Postretirement Benefit Plans":0.0,"Non Current Deferred Revenue":3500000.0,"Non Current Deferred Taxes Liabilities":61700000.0,"Long Term Debt And Capital Lease Obligation":64200000.0,"Long Term Capital Lease Obligation":34900000.0,"Long Term Debt":29300000.0,"Long Term Provisions":1600000.0,"Current Liabilities":203600000.0,"Other Current Liabilities":2900000.0,"Current Deferred Taxes Liabilities":0.0,"Current Debt And Capital Lease Obligation":11800000.0,"Current Capital Lease Obligation":11800000.0,"Pensionand Other Post Retirement Benefit Plans Current":0.0,"Current Provisions":2900000.0,"Payables":67000000.0,"Other Payable":10100000.0,"Total Tax Payable":26700000.0,"Accounts Payable":30200000.0,"Total Assets":1476300000.0,"Total Non Current Assets":1150400000.0,"Non Current Deferred Taxes Assets":1100000.0,"Goodwill And Other Intangible Assets":1078000000.0,"Other Intangible Assets":385400000.0,"Goodwill":692600000.0,"Net PPE":70300000.0,"Accumulated Depreciation":-29800000.0,"Gross PPE":100100000.0,"Machinery Furniture Equipment":34800000.0,"Buildings And Improvements":48300000.0,"Land And Improvements":17000000.0,"Properties":0.0,"Current Assets":325900000.0,"Prepaid Assets":13100000.0,"Other Receivables":58500000.0,"Taxes Receivable":4200000.0,"Accounts Receivable":148900000.0,"Allowance For Doubtful Accounts Receivable":-2300000.0,"Gross Accounts Receivable":151200000.0,"Cash Cash Equivalents And Short Term Investments":101200000.0,"Cash And Cash Equivalents":101200000.0,"Cash Equivalents":6400000.0,"Cash Financial":94800000.0},"2021":{"Treasury Shares Number":55896.0,"Tradeand Other Payables Non Current":200000.0,"Other Current Liabilities":1500000.0,"Current Deferred Taxes Liabilities":0.0}},"cash_flow":{"2025":{"Free Cash Flow":43200000.0,"Repurchase Of Capital Stock":0.0,"Capital Expenditure":-25600000.0,"End Cash Position":32600000.0,"Beginning Cash Position":61500000.0,"Effect Of Exchange Rate Changes":-1200000.0,"Changes In Cash":-27700000.0,"Financing Cash Flow":-76700000.0,"Interest Paid Cff":-5000000.0,"Cash Dividends Paid":-45900000.0,"Common Stock Dividend Paid":-45900000.0,"Net Common Stock Issuance":0.0,"Common Stock Payments":0.0,"Net Issuance Payments Of Debt":-17200000.0,"Net Long Term Debt Issuance":-17200000.0,"Investing Cash Flow":-19800000.0,"Net Other Investing Changes":5000000.0,"Interest Received Cfi":800000.0,"Net Business Purchase And Sale":0.0,"Purchase Of Business":0.0,"Net Intangibles Purchase And Sale":-22200000.0,"Purchase Of Intangibles":-22200000.0,"Net PPE Purchase And Sale":-3400000.0,"Purchase Of PPE":-3400000.0,"Operating Cash Flow":68800000.0,"Taxes Refund Paid":-17300000.0,"Change In Working Capital":13500000.0,"Change In Payable":11800000.0,"Change In Receivables":1700000.0,"Other Non Cash Items":5500000.0,"Stock Based Compensation":3800000.0,"Depreciation And Amortization":75000000.0,"Amortization Cash Flow":63600000.0,"Depreciation":11400000.0,"Gain Loss On Sale Of Business":0.0,"Net Income From Continuing Operations":-99700000.0},"2024":{"Free Cash Flow":32200000.0,"Repurchase Of Capital Stock":-30400000.0,"Repayment Of Debt":-64100000.0,"Issuance Of Debt":87000000.0,"Issuance Of Capital Stock":0.0,"Capital Expenditure":-43100000.0,"End Cash Position":61500000.0,"Beginning Cash Position":76200000.0,"Effect Of Exchange Rate Changes":-5200000.0,"Changes In Cash":-9500000.0,"Financing Cash Flow":-67100000.0,"Interest Paid Cff":-4600000.0,"Cash Dividends Paid":-45500000.0,"Common Stock Dividend Paid":-45500000.0,"Net Common Stock Issuance":-30400000.0,"Common Stock Payments":-30400000.0,"Common Stock Issuance":0.0,"Net Issuance Payments Of Debt":22900000.0,"Net Long Term Debt Issuance":22900000.0,"Long Term Debt Payments":-64100000.0,"Long Term Debt Issuance":87000000.0,"Investing Cash Flow":-17700000.0,"Net Other Investing Changes":25000000.0,"Interest Received Cfi":900000.0,"Net Business Purchase And Sale":-500000.0,"Purchase Of Business":-500000.0,"Net Intangibles Purchase And Sale":-40500000.0,"Purchase Of Intangibles":-40500000.0,"Net PPE Purchase And Sale":-2600000.0,"Purchase Of PPE":-2600000.0,"Operating Cash Flow":75300000.0,"Taxes Refund Paid":-20200000.0,"Change In Working Capital":-33100000.0,"Change In Payable":-26300000.0,"Change In Receivables":-6800000.0,"Other Non Cash Items":4200000.0,"Stock Based Compensation":2900000.0,"Depreciation And Amortization":69300000.0,"Amortization Cash Flow":54800000.0,"Depreciation":14500000.0,"Gain Loss On Sale Of Business":-30000000.0,"Net Income From Continuing Operations":60000000.0},"2023":{"Free Cash Flow":67200000.0,"Repurchase Of Capital Stock":-19400000.0,"Repayment Of Debt":-25000000.0,"Issuance Of Debt":49000000.0,"Issuance Of Capital Stock":100000.0,"Capital Expenditure":-40300000.0,"End Cash Position":76200000.0,"Beginning Cash Position":101200000.0,"Effect Of Exchange Rate Changes":-5200000.0,"Changes In Cash":-19800000.0,"Financing Cash Flow":-56100000.0,"Interest Paid Cff":-2600000.0,"Cash Dividends Paid":-46300000.0,"Common Stock Dividend Paid":-46300000.0,"Net Common Stock Issuance":-19300000.0,"Common Stock Payments":-19400000.0,"Common Stock Issuance":100000.0,"Net Issuance Payments Of Debt":24000000.0,"Net Long Term Debt Issuance":24000000.0,"Long Term Debt Payments":-25000000.0,"Long Term Debt Issuance":49000000.0,"Investing Cash Flow":-71200000.0,"Interest Received Cfi":600000.0,"Net Business Purchase And Sale":-31500000.0,"Purchase Of Business":-31500000.0,"Net Intangibles Purchase And Sale":-36500000.0,"Purchase Of Intangibles":-36500000.0,"Net PPE Purchase And Sale":-3800000.0,"Purchase Of PPE":-3800000.0,"Operating Cash Flow":107500000.0,"Taxes Refund Paid":-21700000.0,"Change In Working Capital":-1700000.0,"Change In Payable":600000.0,"Change In Receivables":-2300000.0,"Other Non Cash Items":4000000.0,"Stock Based Compensation":1800000.0,"Depreciation And Amortization":73600000.0,"Amortization Cash Flow":56900000.0,"Depreciation":16700000.0,"Gain Loss On Sale Of Business":0.0,"Net Income From Continuing Operations":-10900000.0},"2022":{"Free Cash Flow":97900000.0,"Repurchase Of Capital Stock":0.0,"Repayment Of Debt":-25500000.0,"Issuance Of Debt":0.0,"Issuance Of Capital Stock":200000.0,"Capital Expenditure":-29600000.0,"End Cash Position":101200000.0,"Beginning Cash Position":92500000.0,"Effect Of Exchange Rate Changes":8000000.0,"Changes In Cash":700000.0,"Financing Cash Flow":-83200000.0,"Interest Paid Cff":-1400000.0,"Cash Dividends Paid":-41900000.0,"Common Stock Dividend Paid":-41900000.0,"Net Common Stock Issuance":200000.0,"Common Stock Payments":0.0,"Common Stock Issuance":200000.0,"Net Issuance Payments Of Debt":-25500000.0,"Net Long Term Debt Issuance":-25500000.0,"Long Term Debt Payments":-25500000.0,"Long Term Debt Issuance":0.0,"Investing Cash Flow":-43600000.0,"Interest Received Cfi":100000.0,"Net Business Purchase And Sale":-14100000.0,"Sale Of Business":0.0,"Purchase Of Business":-14100000.0,"Net Intangibles Purchase And Sale":-24300000.0,"Purchase Of Intangibles":-24300000.0,"Net PPE Purchase And Sale":-5300000.0,"Purchase Of PPE":-5300000.0,"Operating Cash Flow":127500000.0,"Taxes Refund Paid":-21300000.0,"Change In Working Capital":-8700000.0,"Change In Payable":-3100000.0,"Change In Receivables":-5600000.0,"Other Non Cash Items":3100000.0,"Stock Based Compensation":3200000.0,"Depreciation And Amortization":68000000.0,"Amortization Cash Flow":50100000.0,"Depreciation":17900000.0,"Net Income From Continuing Operations":83200000.0},"2021":{"Repayment Of Debt":-17100000.0,"Issuance Of Capital Stock":600000.0,"Common Stock Issuance":600000.0,"Long Term Debt Payments":-17100000.0,"Net Other Investing Changes":-6400000.0,"Sale Of Business":55000000.0}},"quarterly_income":{}}